{
    "order": 0,
    "index_patterns": [
        "dmd_claims_timeline-*"
    ],
    "settings": {
        "index": {
            "number_of_shards": "1"
        }
    },
    "mappings": {
        "properties": {
            "lineOfBusiness": {
                "type": "text",
                "fields": {
                    "keyword": {
                        "ignore_above": 256,
                        "type": "keyword"
                    }
                }
            },
            "secRole": {
                "type": "text",
                "fields": {
                    "keyword": {
                        "ignore_above": 256,
                        "type": "keyword"
                    }
                }
            },
            "eventSource": {
                "type": "text",
                "fields": {
                    "keyword": {
                        "ignore_above": 256,
                        "type": "keyword"
                    }
                }
            },
            "claimRefId": {
                "type": "text",
                "fields": {
                    "keyword": {
                        "ignore_above": 256,
                        "type": "keyword"
                    }
                }
            },
            "eventType": {
                "type": "text",
                "fields": {
                    "keyword": {
                        "ignore_above": 256,
                        "type": "keyword"
                    }
                }
            },
            "eventReason": {
                "type": "text",
                "fields": {
                    "keyword": {
                        "ignore_above": 256,
                        "type": "keyword"
                    }
                }
            },
            "seqClaimId": {
                "type": "long"
            },
            "claimType": {
                "type": "text",
                "fields": {
                    "keyword": {
                        "ignore_above": 256,
                        "type": "keyword"
                    }
                }
            },
            "@timestamp": {
                "type": "date"
            },
            "insertDatetime": {
                "type": "date"
            },
            "dateReceived": {
                "type": "date"
            },
            "eventTriggerType": {
                "type": "text",
                "fields": {
                    "keyword": {
                        "ignore_above": 256,
                        "type": "keyword"
                    }
                }
            },
            "@version": {
                "type": "text",
                "fields": {
                    "keyword": {
                        "ignore_above": 256,
                        "type": "keyword"
                    }
                }
            },
            "eventRefId": {
                "type": "long",
                "fields": {
                    "keyword": {
                        "ignore_above": 256,
                        "type": "keyword"
                    }
                }
            },
            "documentId": {
                "type": "text",
                "fields": {
                    "keyword": {
                        "ignore_above": 256,
                        "type": "keyword"
                    }
                }
            },
            "eventGroup": {
                "type": "text",
                "fields": {
                    "keyword": {
                        "ignore_above": 256,
                        "type": "keyword"
                    }
                }
            },
            "claimNumber": {
                "type": "keyword",
                "fields": {
                    "keyword": {
                        "ignore_above": 256,
                        "type": "keyword"
                    }
                }
            }
        }
    },
    "aliases": {}
}